texteval/__init__.py
texteval/data_store.py
texteval/evaluate.py
texteval/summarize.py
texteval-1.0.5.dist-info/LICENSE.md
texteval-1.0.5.dist-info/METADATA
texteval-1.0.5.dist-info/WHEEL
texteval-1.0.5.dist-info/top_level.txt
texteval-1.0.5.dist-info/RECORD
