Metadata-Version: 2.1
Name: texteval
Version: 1.0.5
Summary: Small python package to calculate the sentence similarity metrics.
Home-page: UNKNOWN
Author: Dipankar
Author-email: dipankarmedhi11@gmail.com
License: MIT
Keywords: sentence similarity text python metrics cosine rouge bleu
Platform: UNKNOWN
Classifier: Programming Language :: Python :: 3
Classifier: Programming Language :: Python :: 3.8
Classifier: Programming Language :: Python :: 3.9
Classifier: License :: OSI Approved :: MIT License
Classifier: Operating System :: OS Independent
Classifier: Intended Audience :: Developers
Requires-Python: >= 3.8
Requires-Dist: nltk ==3.8.1
Requires-Dist: rouge ==1.0.1
Requires-Dist: scikit-learn ==1.3.2
